nmrtoolbox/ConfigObject.py
nmrtoolbox/__init__.py
nmrtoolbox/mask.py
nmrtoolbox/peak.py
nmrtoolbox/roc.py
nmrtoolbox/spectrum.py
nmrtoolbox/strip_plot.py
nmrtoolbox/util.py
nmrtoolbox-11.1.dist-info/METADATA
nmrtoolbox-11.1.dist-info/WHEEL
nmrtoolbox-11.1.dist-info/entry_points.txt
nmrtoolbox-11.1.dist-info/licenses/LICENSE
nmrtoolbox-11.1.dist-info/RECORD
