Metadata-Version: 2.1
Name: nmrtoolbox
Version: 11.1
Summary: simple utility for parsing and working with NMR peak tables, including ROC analysis
Project-URL: Homepage, https://nmrbox.nmrhub.org/
Author-email: Adam Schuyler <schuyler@uchc.edu>, D Levi Craft <darcraft@uchc.edu>
License-Expression: MIT
License-File: LICENSE
Classifier: License :: OSI Approved :: MIT License
Classifier: Operating System :: OS Independent
Classifier: Programming Language :: Python :: 3
Requires-Python: ~=3.7
Requires-Dist: matplotlib~=3.6
Requires-Dist: nmrglue~=0.9
Requires-Dist: numpy~=1.23
Requires-Dist: scipy~=1.9
